akips/__init__.py
akips/exceptions.py
akips-0.5.0.dist-info/LICENSE
akips-0.5.0.dist-info/METADATA
akips-0.5.0.dist-info/WHEEL
akips-0.5.0.dist-info/RECORD
