Metadata-Version: 2.1
Name: akips
Version: 0.5.0
Summary: Module to interact with the AKiPS Network Monitoring Software API interface
Home-page: https://github.com/unc-network/akips
License: MIT
Author: William E Whitaker
Author-email: will.whitaker@unc.edu
Requires-Python: >=3.9,<4.0
Classifier: License :: OSI Approved :: MIT License
Classifier: Programming Language :: Python :: 3
Classifier: Programming Language :: Python :: 3.9
Classifier: Programming Language :: Python :: 3.10
Classifier: Programming Language :: Python :: 3.11
Classifier: Programming Language :: Python :: 3.12
Classifier: Programming Language :: Python :: 3.13
Requires-Dist: pytz
Requires-Dist: requests (>=2.31)
Project-URL: Repository, https://github.com/unc-network/akips
